nonebot_plugin_cooldown/__init__.py
nonebot_plugin_cooldown/config.py
nonebot_plugin_cooldown/cooldown.py
nonebot_plugin_cooldown/rule.py
nonebot_plugin_cooldown-1.0.5.dist-info/LICENSE
nonebot_plugin_cooldown-1.0.5.dist-info/WHEEL
nonebot_plugin_cooldown-1.0.5.dist-info/METADATA
nonebot_plugin_cooldown-1.0.5.dist-info/RECORD
