Metadata-Version: 2.1
Name: nonebot-plugin-cooldown
Version: 1.0.5
Summary: A Cooldown Event Managing Plugin for Nonebot 2
License: MIT
Author: Satoshi Jek
Author-email: jks15satoshi@gmail.com
Requires-Python: >=3.8,<4.0
Classifier: License :: OSI Approved :: MIT License
Classifier: Programming Language :: Python :: 3
Classifier: Programming Language :: Python :: 3.8
Classifier: Programming Language :: Python :: 3.9
Requires-Dist: apscheduler (>=3.7.0,<4.0.0)
Requires-Dist: nonebot2 (>=2.0.0-alpha.8,<3.0.0)
